setup.py
pyretry/__init__.py
pyretry/pyretry.py
pyretry/tests.py
pyretry.egg-info/PKG-INFO
pyretry.egg-info/SOURCES.txt
pyretry.egg-info/dependency_links.txt
pyretry.egg-info/top_level.txt